amcl/__init__.py
amcl/_amcl_impl.abi3.so
amcl-0.1.2.dist-info/METADATA
amcl-0.1.2.dist-info/WHEEL
amcl-0.1.2.dist-info/RECORD
amcl-0.1.2.dist-info/licenses/LICENSE
