Metadata-Version: 2.1
Name: amcl
Version: 0.1.2
Summary: AMCL Python Bindings
Author-Email: "Joshua J. Damanik" <joshuajdmk@gmail.com>
Classifier: License :: OSI Approved :: GNU General Public License v3 (GPLv3)
Classifier: Programming Language :: Python :: 3
Classifier: Programming Language :: Python :: 3.8
Classifier: Programming Language :: Python :: 3.9
Classifier: Programming Language :: Python :: 3.10
Classifier: Programming Language :: Python :: 3.11
Classifier: Programming Language :: Python :: 3.12
Classifier: Programming Language :: Python :: 3.13
Classifier: Programming Language :: C++
Classifier: Topic :: Scientific/Engineering
Classifier: Operating System :: OS Independent
Project-URL: Homepage, https://github.com/damanikjosh/amcl_python
Requires-Python: <3.14,>=3.8
